README.md
setup.cfg
setup.py
cloudflare_request_header_plugin/__init__.py
cloudflare_request_header_plugin/cloudflare_request_header_provider.py
cloudflare_request_header_plugin.egg-info/PKG-INFO
cloudflare_request_header_plugin.egg-info/SOURCES.txt
cloudflare_request_header_plugin.egg-info/dependency_links.txt
cloudflare_request_header_plugin.egg-info/entry_points.txt
cloudflare_request_header_plugin.egg-info/requires.txt
cloudflare_request_header_plugin.egg-info/top_level.txt